varcity/__init__.py
varcity/client.py
varcity/server.py
varcity-0.1.19.dist-info/METADATA
varcity-0.1.19.dist-info/WHEEL
varcity-0.1.19.dist-info/top_level.txt
varcity-0.1.19.dist-info/RECORD
