Metadata-Version: 2.1
Name: varcity
Version: 0.1.19
Summary: UNKNOWN
Home-page: UNKNOWN
Author: UNKNOWN
Author-email: UNKNOWN
License: UNKNOWN
Platform: UNKNOWN
Requires-Dist: psutil (>=5.5.0)
